djangokit/__init__.py
djangokit/validators.py
djangokit/access/__init__.py
djangokit/access/decorators.py
djangokit/access/functions.py
djangokit/db/__init__.py
djangokit/db/mixins.py
djangokit/db/postgres/__init__.py
djangokit/db/postgres/fields.py
djangokit/forms/__init__.py
djangokit/forms/iso.py
djangokit/forms/postgres.py
djangokit/forms/widgets/__init__.py
djangokit/forms/widgets/selectize.py
djangokit/locale/en/LC_MESSAGES/django.mo
djangokit/locale/en/LC_MESSAGES/django.po
djangokit/locale/ru/LC_MESSAGES/django.mo
djangokit/locale/ru/LC_MESSAGES/django.po
djangokit/logging/__init__.py
djangokit/logging/formatters.py
djangokit/management/__init__.py
djangokit/management/lock.py
djangokit/management/log.py
djangokit/middleware/__init__.py
djangokit/middleware/access.py
djangokit/middleware/profiler.py
djangokit/middleware/sql.py
djangokit/middleware/subdomains.py
djangokit/serializers/__init__.py
djangokit/serializers/objects.py
djangokit/templates/djangokit/widgets/selectize.html
djangokit/templates/djangokit/widgets/selectize_multiple.html
djangokit/templatetags/__init__.py
djangokit/templatetags/bootstrap4.py
djangokit/templatetags/html.py
djangokit/templatetags/json.py
djangokit/templatetags/navigation.py
djangokit/templatetags/os.py
djangokit/utils/__init__.py
djangokit/utils/apps.py
djangokit/utils/crypto.py
djangokit/utils/datetimes.py
djangokit/utils/deep.py
djangokit/utils/encoders.py
djangokit/utils/files.py
djangokit/utils/images.py
djangokit/utils/markdown.py
djangokit/utils/periods.py
djangokit/utils/querysets.py
djangokit/utils/requests.py
djangokit/utils/responses.py
djangokit/utils/strings.py
djangokit/utils/version.py
djangokit/views/__init__.py
djangokit/views/controller.py
djangokit/views/decorators.py
djangokit/views/logreader.py
DjangoKit-0.13.dist-info/AUTHORS
DjangoKit-0.13.dist-info/LICENSE
DjangoKit-0.13.dist-info/METADATA
DjangoKit-0.13.dist-info/WHEEL
DjangoKit-0.13.dist-info/top_level.txt
DjangoKit-0.13.dist-info/RECORD
